rio_tiler_pds/__init__.py
rio_tiler_pds/errors.py
rio_tiler_pds/utils.py
rio_tiler_pds/cbers/__init__.py
rio_tiler_pds/cbers/utils.py
rio_tiler_pds/cbers/aws/__init__.py
rio_tiler_pds/cbers/aws/cbers4.py
rio_tiler_pds/copernicus/__init__.py
rio_tiler_pds/copernicus/aws/__init__.py
rio_tiler_pds/copernicus/aws/dem.py
rio_tiler_pds/landsat/__init__.py
rio_tiler_pds/landsat/utils.py
rio_tiler_pds/landsat/aws/__init__.py
rio_tiler_pds/landsat/aws/landsat_collection2.py
rio_tiler_pds/modis/__init__.py
rio_tiler_pds/modis/modland_grid.py
rio_tiler_pds/modis/utils.py
rio_tiler_pds/modis/aws/__init__.py
rio_tiler_pds/modis/aws/modis_astraea.py
rio_tiler_pds/modis/aws/modis_pds.py
rio_tiler_pds/sentinel/__init__.py
rio_tiler_pds/sentinel/utils.py
rio_tiler_pds/sentinel/aws/__init__.py
rio_tiler_pds/sentinel/aws/sentinel1.py
rio_tiler_pds/sentinel/aws/sentinel2.py
rio_tiler_pds-0.11.0.dist-info/LICENSE.txt
rio_tiler_pds-0.11.0.dist-info/WHEEL
rio_tiler_pds-0.11.0.dist-info/METADATA
rio_tiler_pds-0.11.0.dist-info/RECORD
