Metadata-Version: 2.3
Name: rio-tiler-pds
Version: 0.11.0
Summary: Get mercator tile from cloud hosted dataset such as CBERS-4, Sentinel-2, Sentinel-1 and Landsat-8 AWS PDS.
Keywords: COGEO,Cloud Optimized Geotiff,AWS PDS
Author-email: Vincent Sarago <vincent@developmentseed.com>
Requires-Python: >=3.8
Classifier: Intended Audience :: Information Technology
Classifier: Intended Audience :: Science/Research
Classifier: License :: OSI Approved :: MIT License
Classifier: Programming Language :: Python :: 3.8
Classifier: Programming Language :: Python :: 3.9
Classifier: Programming Language :: Python :: 3.10
Classifier: Programming Language :: Python :: 3.11
Classifier: Programming Language :: Python :: 3.12
Classifier: Programming Language :: Python :: 3.13
Classifier: Topic :: Scientific/Engineering :: GIS
Classifier: Typing :: Typed
Requires-Dist: rio-tiler>=7.0,<8.0
Requires-Dist: boto3
Requires-Dist: pre-commit ; extra == "dev"
Requires-Dist: mkdocs ; extra == "docs"
Requires-Dist: mkdocs-material ; extra == "docs"
Requires-Dist: pygments ; extra == "docs"
Requires-Dist: mkapi ; extra == "docs"
Requires-Dist: pytest ; extra == "test"
Requires-Dist: pytest-cov ; extra == "test"
Project-URL: Documentation, https://cogeotiff.github.io/rio-tiler-pds/
Project-URL: Source, https://github.com/cogeotiff/rio-tiler-pds
Provides-Extra: dev
Provides-Extra: docs
Provides-Extra: test
